accio/__init__.py
accio/cli.py
accio_client-0.0.2.dist-info/LICENSE
accio_client-0.0.2.dist-info/METADATA
accio_client-0.0.2.dist-info/WHEEL
accio_client-0.0.2.dist-info/entry_points.txt
accio_client-0.0.2.dist-info/top_level.txt
accio_client-0.0.2.dist-info/RECORD
